__init__.py
guided_interpolation/__init__.py
guided_interpolation/guided_interpolation.py
guided_interpolation/kriging.py
tests/__init__.py
tests/test_kriging.py
utils/__init__.py
utils/pseudowell.py
utils/spatial_analysis.py
guided_interpolation-0.0.2.dist-info/LICENSE.md
guided_interpolation-0.0.2.dist-info/METADATA
guided_interpolation-0.0.2.dist-info/WHEEL
guided_interpolation-0.0.2.dist-info/top_level.txt
guided_interpolation-0.0.2.dist-info/RECORD
